{
  "nameOfBrand": "Artdeco",
  "spaceKey": " ",
  "specialCharacters": "*-/,",
  "titleSubCategory": "Косметика для очей",
  "filterProductName": "Блиск для губ",
  "productName": "крем",
  "categoryTitle": "Декоративна косметика",
  "category": "Макіяж",
  "categoryTitleText": "Декоративна косметика",
  "subCategory": "Очі",
  "deliveryCity": " харків",
  "productAddToCart": "Artdeco Hydra Lip Booster",
  "titleMainPageru": "MAKEUP - интернет-магазин косметики и парфюмерии №1",
  "titleMainPageUA": "MAKEUP - інтернет-магазин косметики та парфумерії №1",
  "subCategoryTitle": "Косметика для очей"
}